activate.bat
pypi.bat
setup.cfg
setup.py
vcard_split.py
vcard_split.egg-info/PKG-INFO
vcard_split.egg-info/SOURCES.txt
vcard_split.egg-info/dependency_links.txt
vcard_split.egg-info/entry_points.txt
vcard_split.egg-info/requires.txt
vcard_split.egg-info/top_level.txt