Metadata-Version: 1.0
Name: vcard-split
Version: 0.2dev-r2010
Summary:         Splits one vcard file (*.vcf) to many vcard files        with one vcard per file. Useful for import contacts to phones,         thats do not support multiple vcard in one file.         Supprt unicode cyrillic characters.         Консольная программа для разбиения одного большлго файла с контактами в формате VCARD (*.vcf)        на несколько файлов содержащих один контакт. Полезна для импорта контактов в телефон,        который не поддерживает несколько контактов в одном файле. П
Home-page: UNKNOWN
Author: mail@dtatarkin.ru
Author-email: mail@dtatarkin.ru
License: PSF
Keywords: vcard split
Platform: UNKNOWN
Classifier: Development Status :: 4 - Beta
Classifier: Environment :: Console
Classifier: Intended Audience :: End Users/Desktop
Classifier: Intended Audience :: System Administrators
Classifier: License :: OSI Approved :: Python Software Foundation License
Classifier: Operating System :: OS Independent
Classifier: Programming Language :: Python
Classifier: Programming Language :: Python :: 2.6
Classifier: Topic :: Communications :: Email :: Address Book
Classifier: Topic :: Communications :: Telephony
Classifier: Topic :: Text Processing
